{"Accepted,Accepted,Accepted": 297, "Accepted,Accepted,Queued": 66, "Accepted,Accepted,Completed": 1772, "Accepted,Unmatched,Unmatched": 46, "Queued,Accepted,Accepted": 511, "Queued,Accepted,Queued": 2, "Queued,Queued,Queued": 38, "Accepted,Accepted,Accepted,Completed": 175, "Accepted,Accepted,Queued,Accepted": 172, "Accepted,Accepted,Completed,Accepted": 133, "Accepted,Accepted,Completed,Completed": 326, "Accepted,Unmatched,Unmatched,Accepted": 30, "Queued,Accepted,Accepted,Completed": 129, "Queued,Accepted,Queued,Queued": 45, "Queued,Accepted,Completed,Completed": 337, "Queued,Accepted,Completed,Unmatched": 86, "Queued,Queued,Completed,Completed": 71, "Accepted,Accepted,Accepted,Accepted,Accepted": 197, "Accepted,Accepted,Accepted,Accepted,Completed": 97, "Accepted,Accepted,Accepted,Queued,Accepted": 63, "Accepted,Accepted,Accepted,Queued,Queued": 525, "Accepted,Accepted,Accepted,Completed,Completed": 376, "Accepted,Accepted,Queued,Accepted,Accepted": 36, "Accepted,Accepted,Queued,Accepted,Completed": 48, "Accepted,Accepted,Queued,Queued,Queued": 77, "Accepted,Accepted,Completed,Accepted,Queued": 104, "Accepted,Accepted,Completed,Accepted,Completed": 87, "Accepted,Accepted,Completed,Completed,Queued": 7, "Queued,Accepted,Accepted,Accepted,Accepted": 40, "Queued,Accepted,Accepted,Completed,Completed": 35, "Queued,Accepted,Queued,Queued,Accepted": 20, "Queued,Accepted,Queued,Queued,Queued": 23, "Queued,Accepted,Completed,Completed,Completed": 104, "Queued,Queued,Queued,Accepted,Completed": 107, "Accepted,Accepted,Accepted,Accepted,Queued,Accepted": 106, "Accepted,Accepted,Accepted,Queued,Accepted,Accepted": 192, "Accepted,Accepted,Accepted,Queued,Accepted,Queued": 41, "Accepted,Accepted,Queued,Accepted,Accepted,Queued": 286, "Accepted,Accepted,Queued,Accepted,Queued,Accepted": 6, "Accepted,Accepted,Queued,Accepted,Completed,Completed": 377, "Accepted,Accepted,Queued,Queued,Completed,Completed": 164, "Accepted,Accepted,Completed,Accepted,Queued,Accepted": 72, "Accepted,Accepted,Completed,Accepted,Completed,Queued": 145, "Queued,Accepted,Accepted,Accepted,Accepted,Accepted": 33, "Queued,Accepted,Accepted,Accepted,Accepted,Queued": 18, "Queued,Accepted,Accepted,Completed,Completed,Accepted": 135, "Queued,Accepted,Completed,Completed,Completed,Completed": 78, "Queued,Queued,Queued,Accepted,Completed,Accepted": 45, "Queued,Queued,Completed,Completed,Accepted,Accepted": 10, "Accepted,Accepted,Accepted,Accepted,Queued,Accepted,Queued": 106, "Accepted,Accepted,Accepted,Queued,Accepted,Accepted,Accepted": 147, "Accepted,Accepted,Accepted,Queued,Accepted,Queued,Accepted": 7, "Accepted,Accepted,Accepted,Completed,Unmatched,Accepted,Accepted": 20, "Accepted,Accepted,Queued,Accepted,Accepted,Accepted,Accepted": 61, "Accepted,Accepted,Queued,Accepted,Accepted,Queued,Accepted": 70, "Accepted,Accepted,Queued,Accepted,Accepted,Completed,Accepted": 179, "Accepted,Accepted,Queued,Accepted,Accepted,Completed,Completed": 363, "Accepted,Accepted,Queued,Accepted,Queued,Accepted,Accepted": 190, "Accepted,Accepted,Queued,Accepted,Queued,Accepted,Queued": 141, "Accepted,Accepted,Completed,Accepted,Completed,Queued,Accepted": 83, "Accepted,Accepted,Completed,Accepted,Completed,Queued,Queued": 123, "Queued,Accepted,Accepted,Accepted,Accepted,Queued,Queued": 180, "Queued,Accepted,Accepted,Accepted,Completed,Accepted,Queued": 18, "Queued,Accepted,Accepted,Queued,Accepted,Accepted,Accepted": 200, "Queued,Accepted,Accepted,Queued,Accepted,Queued,Accepted": 97, "Queued,Accepted,Accepted,Completed,Completed,Accepted,Queued": 1, "Queued,Accepted,Completed,Completed,Completed,Completed,Completed": 42, "Queued,Queued,Completed,Completed,Accepted,Accepted,Accepted": 290, "Queued,Queued,Completed,Completed,Accepted,Accepted,Queued": 54, "Accepted,Accepted,Accepted,Accepted,Queued,Accepted,Queued,Accepted": 61, "Accepted,Accepted,Accepted,Accepted,Queued,Accepted,Queued,Completed": 345, "Accepted,Accepted,Accepted,Queued,Accepted,Accepted,Accepted,Completed": 82, "Accepted,Accepted,Accepted,Queued,Accepted,Queued,Accepted,Accepted": 93, "Accepted,Accepted,Accepted,Queued,Accepted,Queued,Queued,Completed": 94, "Accepted,Accepted,Accepted,Queued,Queued,Accepted,Completed,Unmatched": 4, "Accepted,Accepted,Queued,Accepted,Accepted,Accepted,Accepted,Accepted": 123, "Accepted,Accepted,Queued,Accepted,Accepted,Accepted,Accepted,Queued": 44, "Accepted,Accepted,Queued,Accepted,Accepted,Accepted,Queued,Queued": 3, "Accepted,Accepted,Queued,Accepted,Accepted,Accepted,Completed,Completed": 156, "Accepted,Accepted,Queued,Accepted,Accepted,Queued,Accepted,Accepted": 256, "Accepted,Accepted,Queued,Accepted,Accepted,Queued,Completed,Unmatched": 92, "Accepted,Accepted,Queued,Accepted,Accepted,Completed,Accepted,Accepted": 42, "Accepted,Accepted,Queued,Accepted,Accepted,Completed,Completed,Accepted": 49, "Accepted,Accepted,Queued,Accepted,Accepted,Completed,Completed,Queued": 239, "Accepted,Accepted,Queued,Accepted,Accepted,Completed,Unmatched,Accepted": 7, "Accepted,Accepted,Queued,Accepted,Queued,Accepted,Queued,Unmatched": 193, "Accepted,Accepted,Queued,Queued,Completed,Completed,Accepted,Queued": 271, "Accepted,Accepted,Queued,Queued,Completed,Completed,Completed,Accepted": 180, "Accepted,Accepted,Completed,Accepted,Queued,Accepted,Accepted,Queued": 2, "Accepted,Accepted,Completed,Accepted,Queued,Accepted,Accepted,Completed": 59, "Accepted,Accepted,Completed,Accepted,Completed,Queued,Accepted,Completed": 128, "Queued,Accepted,Accepted,Accepted,Accepted,Accepted,Completed,Completed": 64, "Queued,Accepted,Accepted,Accepted,Accepted,Queued,Queued,Queued": 71, "Queued,Accepted,Accepted,Accepted,Completed,Accepted,Queued,Accepted": 39, "Queued,Accepted,Accepted,Accepted,Completed,Accepted,Queued,Completed": 10, "Queued,Accepted,Accepted,Accepted,Completed,Unmatched,Accepted,Completed": 25, "Queued,Accepted,Accepted,Queued,Accepted,Accepted,Accepted,Queued": 35, "Queued,Accepted,Completed,Completed,Completed,Completed,Completed,Queued": 5, "Queued,Queued,Queued,Accepted,Completed,Accepted,Accepted,Accepted": 25, "Accepted,Accepted,Accepted,Accepted,Queued,Accepted,Queued,Accepted,Queued": 2, "Accepted,Accepted,Accepted,Accepted,Queued,Accepted,Queued,Completed,Queued": 1, "Accepted,Accepted,Accepted,Queued,Accepted,Accepted,Accepted,Accepted,Accepted": 3, "Accepted,Accepted,Accepted,Queued,Accepted,Queued,Accepted,Accepted,Accepted": 56, "Accepted,Accepted,Queued,Accepted,Accepted,Accepted,Accepted,Accepted,Accepted": 197, "Accepted,Accepted,Queued,Accepted,Accepted,Accepted,Accepted,Completed,Completed": 102, "Accepted,Accepted,Queued,Accepted,Accepted,Accepted,Queued,Accepted,Accepted": 44, "Accepted,Accepted,Queued,Accepted,Accepted,Accepted,Queued,Accepted,Queued": 97, "Accepted,Accepted,Queued,Accepted,Accepted,Accepted,Queued,Queued,Unmatched": 52, "Accepted,Accepted,Queued,Accepted,Accepted,Queued,Accepted,Accepted,Unmatched": 57, "Accepted,Accepted,Queued,Accepted,Accepted,Queued,Accepted,Queued,Accepted": 105, "Accepted,Accepted,Queued,Accepted,Accepted,Completed,Accepted,Accepted,Queued": 11, "Accepted,Accepted,Queued,Accepted,Queued,Accepted,Accepted,Accepted,Accepted": 140, "Accepted,Accepted,Queued,Accepted,Queued,Accepted,Accepted,Accepted,Completed": 46, "Accepted,Accepted,Queued,Accepted,Queued,Accepted,Accepted,Completed,Completed": 93, "Accepted,Accepted,Queued,Accepted,Queued,Accepted,Queued,Accepted,Accepted": 123, "Accepted,Accepted,Queued,Accepted,Queued,Accepted,Queued,Accepted,Queued": 329, "Accepted,Accepted,Queued,Accepted,Queued,Accepted,Queued,Accepted,Completed": 43, "Accepted,Accepted,Queued,Queued,Completed,Completed,Completed,Accepted,Accepted": 109, "Accepted,Accepted,Queued,Queued,Completed,Completed,Completed,Accepted,Queued": 33, "Accepted,Accepted,Completed,Accepted,Queued,Accepted,Accepted,Queued,Completed": 22, "Accepted,Accepted,Completed,Accepted,Completed,Queued,Accepted,Completed,Accepted": 106, "Accepted,Accepted,Completed,Accepted,Completed,Queued,Queued,Queued,Completed": 9, "Queued,Accepted,Accepted,Accepted,Accepted,Queued,Queued,Queued,Completed": 28, "Queued,Accepted,Accepted,Accepted,Completed,Unmatched,Accepted,Completed,Accepted": 8, "Queued,Accepted,Accepted,Queued,Accepted,Accepted,Accepted,Queued,Completed": 17, "Queued,Accepted,Accepted,Queued,Accepted,Queued,Accepted,Accepted,Queued": 217, "Queued,Accepted,Accepted,Queued,Accepted,Queued,Accepted,Accepted,Completed": 279, "Queued,Accepted,Accepted,Queued,Accepted,Queued,Accepted,Completed,Queued": 87, "Queued,Accepted,Accepted,Completed,Completed,Accepted,Queued,Queued,Unmatched": 13, "Queued,Accepted,Completed,Completed,Completed,Completed,Completed,Completed,Accepted": 46, "Queued,Queued,Queued,Accepted,Completed,Accepted,Accepted,Accepted,Accepted": 35, "Queued,Queued,Queued,Accepted,Completed,Accepted,Accepted,Queued,Accepted": 39, "Accepted,Accepted,Accepted,Accepted,Queued,Accepted,Queued,Completed,Queued,Unmatched": 90, "Accepted,Accepted,Accepted,Accepted,Queued,Accepted,Queued,Completed,Unmatched,Queued": 327, "Accepted,Accepted,Accepted,Queued,Accepted,Accepted,Accepted,Accepted,Accepted,Accepted": 325, "Accepted,Accepted,Accepted,Queued,Accepted,Accepted,Accepted,Accepted,Completed,Completed": 66, "Accepted,Accepted,Queued,Accepted,Accepted,Accepted,Accepted,Accepted,Accepted,Completed": 64, "Accepted,Accepted,Queued,Accepted,Accepted,Accepted,Accepted,Accepted,Queued,Accepted": 44, "Accepted,Accepted,Queued,Accepted,Accepted,Accepted,Accepted,Accepted,Completed,Completed": 44, "Accepted,Accepted,Queued,Accepted,Accepted,Accepted,Queued,Accepted,Accepted,Unmatched": 231, "Accepted,Accepted,Queued,Accepted,Accepted,Queued,Accepted,Accepted,Completed,Queued": 51, "Accepted,Accepted,Queued,Accepted,Accepted,Queued,Accepted,Accepted,Completed,Completed": 60, "Accepted,Accepted,Queued,Accepted,Accepted,Queued,Accepted,Queued,Accepted,Accepted": 8, "Accepted,Accepted,Queued,Accepted,Accepted,Completed,Accepted,Accepted,Queued,Queued": 16, "Accepted,Accepted,Queued,Accepted,Accepted,Completed,Accepted,Accepted,Completed,Accepted": 167, "Accepted,Accepted,Queued,Accepted,Accepted,Completed,Completed,Accepted,Completed,Queued": 22, "Accepted,Accepted,Queued,Accepted,Accepted,Completed,Completed,Queued,Accepted,Completed": 24, "Accepted,Accepted,Queued,Accepted,Accepted,Completed,Completed,Queued,Unmatched,Unmatched": 119, "Accepted,Accepted,Queued,Accepted,Queued,Accepted,Accepted,Accepted,Accepted,Completed": 78, "Accepted,Accepted,Queued,Accepted,Queued,Accepted,Accepted,Accepted,Queued,Unmatched": 69, "Accepted,Accepted,Queued,Accepted,Queued,Accepted,Accepted,Accepted,Completed,Queued": 108, "Accepted,Accepted,Queued,Accepted,Queued,Accepted,Queued,Accepted,Queued,Accepted": 3, "Accepted,Accepted,Queued,Accepted,Queued,Accepted,Queued,Accepted,Completed,Completed": 58, "Accepted,Accepted,Queued,Accepted,Completed,Completed,Unmatched,Accepted,Accepted,Completed": 17, "Accepted,Accepted,Queued,Accepted,Completed,Completed,Unmatched,Completed,Accepted,Accepted": 18, "Accepted,Accepted,Queued,Queued,Completed,Completed,Completed,Accepted,Accepted,Queued": 67, "Accepted,Accepted,Queued,Queued,Completed,Completed,Completed,Accepted,Queued,Completed": 13, "Accepted,Accepted,Completed,Accepted,Queued,Accepted,Accepted,Queued,Completed,Completed": 274, "Accepted,Accepted,Completed,Accepted,Queued,Accepted,Accepted,Completed,Queued,Queued": 6, "Queued,Accepted,Completed,Completed,Completed,Completed,Completed,Queued,Accepted,Accepted": 221, "Queued,Accepted,Completed,Completed,Completed,Completed,Completed,Completed,Accepted,Queued": 125, "Queued,Queued,Queued,Accepted,Completed,Accepted,Accepted,Queued,Accepted,Queued": 8, "Queued,Queued,Queued,Accepted,Completed,Accepted,Accepted,Queued,Accepted,Unmatched": 101, "Accepted,Accepted,Accepted,Queued,Accepted,Accepted,Accepted,Accepted,Accepted,Accepted,Completed": 44, "Accepted,Accepted,Accepted,Queued,Accepted,Accepted,Accepted,Accepted,Accepted,Completed,Completed": 6, "Accepted,Accepted,Accepted,Queued,Accepted,Queued,Accepted,Accepted,Accepted,Accepted,Completed": 122, "Accepted,Accepted,Queued,Accepted,Accepted,Accepted,Accepted,Accepted,Queued,Accepted,Completed": 134, "Accepted,Accepted,Queued,Accepted,Accepted,Accepted,Accepted,Accepted,Completed,Unmatched,Accepted": 134, "Accepted,Accepted,Queued,Accepted,Accepted,Accepted,Queued,Accepted,Queued,Accepted,Accepted": 151, "Accepted,Accepted,Queued,Accepted,Accepted,Queued,Accepted,Queued,Accepted,Accepted,Completed": 71, "Accepted,Accepted,Queued,Accepted,Accepted,Queued,Accepted,Queued,Accepted,Queued,Completed": 11, "Accepted,Accepted,Queued,Accepted,Accepted,Completed,Accepted,Accepted,Queued,Queued,Accepted": 4, "Accepted,Accepted,Queued,Accepted,Accepted,Completed,Accepted,Accepted,Queued,Queued,Queued": 25, "Accepted,Accepted,Queued,Accepted,Accepted,Completed,Accepted,Accepted,Completed,Queued,Completed": 64, "Accepted,Accepted,Queued,Accepted,Queued,Accepted,Accepted,Accepted,Accepted,Accepted,Completed": 111, "Accepted,Accepted,Queued,Accepted,Queued,Accepted,Accepted,Accepted,Completed,Accepted,Queued": 236, "Accepted,Accepted,Queued,Accepted,Queued,Accepted,Queued,Accepted,Queued,Accepted,Queued": 159, "Accepted,Accepted,Queued,Accepted,Queued,Accepted,Queued,Accepted,Completed,Accepted,Accepted": 10, "Accepted,Accepted,Queued,Accepted,Queued,Accepted,Queued,Accepted,Completed,Accepted,Queued": 59, "Accepted,Accepted,Queued,Queued,Completed,Completed,Completed,Accepted,Accepted,Accepted,Accepted": 164, "Accepted,Accepted,Queued,Queued,Completed,Completed,Completed,Accepted,Accepted,Queued,Completed": 239, "Accepted,Accepted,Completed,Accepted,Queued,Accepted,Accepted,Queued,Completed,Completed,Completed": 23, "Accepted,Accepted,Completed,Accepted,Queued,Accepted,Accepted,Completed,Queued,Queued,Completed": 116, "Accepted,Accepted,Completed,Accepted,Completed,Queued,Queued,Queued,Completed,Completed,Completed": 19, "Queued,Accepted,Accepted,Accepted,Accepted,Accepted,Completed,Completed,Accepted,Completed,Accepted": 124, "Queued,Accepted,Accepted,Accepted,Accepted,Queued,Queued,Queued,Completed,Accepted,Accepted": 187, "Queued,Accepted,Accepted,Accepted,Completed,Accepted,Queued,Accepted,Queued,Accepted,Queued": 453, "Queued,Accepted,Accepted,Accepted,Completed,Accepted,Queued,Accepted,Queued,Completed,Queued": 238, "Queued,Accepted,Accepted,Accepted,Completed,Unmatched,Accepted,Completed,Accepted,Accepted,Completed": 208, "Queued,Accepted,Accepted,Queued,Accepted,Queued,Accepted,Accepted,Queued,Completed,Accepted": 59, "Queued,Accepted,Accepted,Queued,Accepted,Queued,Queued,Accepted,Queued,Completed,Completed": 83, "Queued,Accepted,Completed,Completed,Completed,Completed,Completed,Queued,Accepted,Accepted,Queued": 9, "Queued,Accepted,Completed,Completed,Completed,Completed,Completed,Completed,Accepted,Queued,Accepted": 4, "Queued,Accepted,Completed,Completed,Completed,Completed,Completed,Completed,Accepted,Queued,Queued": 269, "Queued,Queued,Queued,Accepted,Completed,Accepted,Accepted,Accepted,Completed,Completed,Completed": 5, "Queued,Queued,Queued,Accepted,Completed,Accepted,Accepted,Queued,Accepted,Accepted,Accepted": 67, "Queued,Queued,Queued,Accepted,Completed,Accepted,Accepted,Queued,Accepted,Queued,Queued": 54, "Accepted,Accepted,Accepted,Accepted,Queued,Accepted,Queued,Completed,Unmatched,Queued,Completed,Accepted": 37, "Accepted,Accepted,Accepted,Queued,Accepted,Accepted,Accepted,Accepted,Accepted,Accepted,Completed,Queued": 76, "Accepted,Accepted,Accepted,Queued,Accepted,Accepted,Accepted,Completed,Queued,Unmatched,Unmatched,Unmatched": 92, "Accepted,Accepted,Accepted,Queued,Accepted,Queued,Accepted,Accepted,Accepted,Accepted,Completed,Queued": 48, "Accepted,Accepted,Queued,Accepted,Accepted,Accepted,Accepted,Accepted,Accepted,Completed,Completed,Queued": 25, "Accepted,Accepted,Queued,Accepted,Accepted,Accepted,Accepted,Accepted,Queued,Accepted,Completed,Queued": 40, "Accepted,Accepted,Queued,Accepted,Accepted,Accepted,Accepted,Accepted,Queued,Accepted,Completed,Unmatched": 45, "Accepted,Accepted,Queued,Accepted,Accepted,Accepted,Accepted,Accepted,Queued,Completed,Unmatched,Completed": 82, "Accepted,Accepted,Queued,Accepted,Accepted,Accepted,Queued,Accepted,Accepted,Queued,Unmatched,Queued": 274, "Accepted,Accepted,Queued,Accepted,Accepted,Accepted,Queued,Accepted,Accepted,Unmatched,Queued,Accepted": 75, "Accepted,Accepted,Queued,Accepted,Accepted,Accepted,Queued,Accepted,Accepted,Unmatched,Queued,Queued": 47, "Accepted,Accepted,Queued,Accepted,Accepted,Queued,Accepted,Queued,Accepted,Accepted,Completed,Completed": 173, "Accepted,Accepted,Queued,Accepted,Accepted,Completed,Accepted,Accepted,Completed,Queued,Completed,Accepted": 50, "Accepted,Accepted,Queued,Accepted,Queued,Accepted,Accepted,Accepted,Accepted,Completed,Unmatched,Accepted": 157, "Accepted,Accepted,Queued,Accepted,Queued,Accepted,Accepted,Accepted,Queued,Queued,Accepted,Queued": 65, "Accepted,Accepted,Queued,Accepted,Queued,Accepted,Accepted,Accepted,Queued,Queued,Accepted,Completed": 55, "Accepted,Accepted,Queued,Accepted,Queued,Accepted,Queued,Accepted,Queued,Accepted,Accepted,Queued": 231, "Accepted,Accepted,Queued,Accepted,Queued,Accepted,Queued,Accepted,Queued,Accepted,Accepted,Completed": 232, "Accepted,Accepted,Queued,Accepted,Queued,Accepted,Queued,Accepted,Completed,Accepted,Accepted,Completed": 3, "Accepted,Accepted,Queued,Queued,Completed,Completed,Completed,Accepted,Accepted,Accepted,Accepted,Queued": 7, "Accepted,Accepted,Queued,Queued,Completed,Completed,Completed,Accepted,Accepted,Queued,Queued,Completed": 46, "Accepted,Accepted,Queued,Queued,Completed,Completed,Completed,Accepted,Accepted,Queued,Completed,Unmatched": 71, "Accepted,Accepted,Queued,Queued,Completed,Completed,Completed,Accepted,Queued,Completed,Accepted,Completed": 50, "Accepted,Accepted,Completed,Accepted,Queued,Accepted,Accepted,Queued,Completed,Queued,Completed,Accepted": 81, "Accepted,Accepted,Completed,Accepted,Queued,Accepted,Accepted,Queued,Completed,Completed,Accepted,Queued": 1, "Accepted,Accepted,Completed,Accepted,Queued,Accepted,Accepted,Completed,Queued,Queued,Completed,Accepted": 159, "Accepted,Accepted,Completed,Accepted,Completed,Queued,Queued,Queued,Completed,Completed,Completed,Accepted": 9, "Accepted,Accepted,Completed,Accepted,Completed,Queued,Queued,Queued,Completed,Completed,Completed,Completed": 107, "Accepted,Accepted,Completed,Accepted,Completed,Queued,Queued,Queued,Completed,Completed,Unmatched,Queued": 39, "Accepted,Accepted,Completed,Accepted,Completed,Queued,Queued,Queued,Completed,Completed,Unmatched,Completed": 88, "Queued,Accepted,Accepted,Accepted,Accepted,Queued,Queued,Queued,Completed,Accepted,Accepted,Accepted": 35, "Queued,Accepted,Accepted,Accepted,Accepted,Queued,Queued,Queued,Completed,Accepted,Accepted,Unmatched": 205, "Queued,Accepted,Accepted,Accepted,Completed,Accepted,Queued,Accepted,Queued,Accepted,Queued,Accepted": 81, "Queued,Accepted,Accepted,Accepted,Completed,Accepted,Queued,Accepted,Queued,Accepted,Queued,Completed": 29, "Queued,Accepted,Accepted,Accepted,Completed,Accepted,Queued,Accepted,Queued,Unmatched,Accepted,Completed": 219, "Queued,Accepted,Accepted,Accepted,Completed,Unmatched,Accepted,Completed,Accepted,Queued,Completed,Accepted": 167, "Queued,Accepted,Accepted,Queued,Accepted,Queued,Accepted,Accepted,Queued,Completed,Accepted,Accepted": 134, "Queued,Accepted,Accepted,Queued,Accepted,Queued,Accepted,Accepted,Queued,Completed,Accepted,Completed": 146, "Queued,Accepted,Accepted,Completed,Completed,Accepted,Queued,Queued,Unmatched,Accepted,Unmatched,Unmatched": 253, "Queued,Accepted,Completed,Completed,Completed,Completed,Completed,Queued,Accepted,Accepted,Accepted,Accepted": 3, "Queued,Accepted,Completed,Completed,Completed,Completed,Completed,Queued,Queued,Unmatched,Accepted,Completed": 21, "Queued,Accepted,Completed,Completed,Completed,Completed,Completed,Completed,Accepted,Queued,Queued,Unmatched": 90, "Queued,Queued,Queued,Accepted,Completed,Accepted,Accepted,Accepted,Completed,Completed,Queued,Accepted": 247, "Queued,Queued,Queued,Accepted,Completed,Accepted,Accepted,Queued,Accepted,Accepted,Accepted,Unmatched": 23, "Queued,Queued,Queued,Accepted,Completed,Accepted,Accepted,Queued,Accepted,Accepted,Completed,Completed": 49, "Queued,Queued,Queued,Accepted,Completed,Accepted,Accepted,Queued,Accepted,Queued,Queued,Queued": 201, "Queued,Queued,Queued,Accepted,Completed,Accepted,Accepted,Queued,Accepted,Queued,Queued,Completed": 123, "Queued,Queued,Queued,Accepted,Completed,Accepted,Accepted,Queued,Accepted,Queued,Completed,Completed": 37, "Queued,Queued,Queued,Accepted,Completed,Accepted,Accepted,Queued,Accepted,Completed,Completed,Queued": 64, "Queued,Queued,Queued,Accepted,Completed,Accepted,Accepted,Queued,Accepted,Completed,Completed,Unmatched": 21, "Queued,Queued,Queued,Accepted,Completed,Accepted,Accepted,Queued,Accepted,Completed,Unmatched,Completed": 101, "Queued,Queued,Queued,Accepted,Completed,Accepted,Accepted,Queued,Accepted,Unmatched,Completed,Completed": 136, "Accepted,Accepted,Accepted,Queued,Accepted,Accepted,Accepted,Accepted,Accepted,Completed,Completed,Accepted,Accepted": 63, "Accepted,Accepted,Accepted,Queued,Accepted,Accepted,Accepted,Accepted,Completed,Completed,Unmatched,Accepted,Accepted": 283, "Accepted,Accepted,Accepted,Queued,Accepted,Accepted,Accepted,Accepted,Completed,Completed,Unmatched,Completed,Queued": 157, "Accepted,Accepted,Accepted,Queued,Accepted,Queued,Accepted,Accepted,Accepted,Accepted,Completed,Accepted,Queued": 71, "Accepted,Accepted,Accepted,Queued,Accepted,Queued,Accepted,Accepted,Accepted,Accepted,Completed,Queued,Accepted": 9, "Accepted,Accepted,Accepted,Queued,Accepted,Queued,Accepted,Accepted,Accepted,Accepted,Completed,Queued,Unmatched": 112, "Accepted,Accepted,Queued,Accepted,Accepted,Queued,Accepted,Queued,Accepted,Accepted,Completed,Accepted,Queued": 83, "Accepted,Accepted,Queued,Accepted,Accepted,Queued,Accepted,Queued,Accepted,Queued,Unmatched,Unmatched,Queued": 81, "Accepted,Accepted,Queued,Accepted,Accepted,Completed,Accepted,Accepted,Completed,Queued,Completed,Completed,Accepted": 141, "Accepted,Accepted,Queued,Accepted,Accepted,Completed,Accepted,Accepted,Completed,Queued,Completed,Completed,Queued": 156, "Accepted,Accepted,Queued,Accepted,Queued,Accepted,Queued,Accepted,Queued,Accepted,Accepted,Queued,Accepted": 46, "Accepted,Accepted,Queued,Accepted,Queued,Accepted,Queued,Accepted,Completed,Accepted,Accepted,Accepted,Completed": 99, "Accepted,Accepted,Queued,Accepted,Queued,Accepted,Queued,Accepted,Completed,Accepted,Accepted,Completed,Accepted": 49, "Accepted,Accepted,Queued,Accepted,Queued,Accepted,Queued,Accepted,Completed,Completed,Accepted,Accepted,Unmatched": 61, "Accepted,Accepted,Queued,Accepted,Queued,Accepted,Queued,Accepted,Completed,Completed,Accepted,Completed,Queued": 47, "Accepted,Accepted,Queued,Queued,Completed,Completed,Completed,Accepted,Accepted,Accepted,Accepted,Queued,Accepted": 13, "Accepted,Accepted,Queued,Queued,Completed,Completed,Completed,Accepted,Accepted,Accepted,Accepted,Queued,Completed": 44, "Accepted,Accepted,Queued,Queued,Completed,Completed,Completed,Accepted,Accepted,Accepted,Completed,Queued,Completed": 14, "Accepted,Accepted,Queued,Queued,Completed,Completed,Completed,Accepted,Accepted,Queued,Queued,Completed,Completed": 202, "Accepted,Accepted,Queued,Queued,Completed,Completed,Completed,Accepted,Queued,Completed,Accepted,Completed,Accepted": 46, "Accepted,Accepted,Completed,Accepted,Completed,Queued,Queued,Queued,Completed,Completed,Completed,Accepted,Queued": 55, "Queued,Accepted,Accepted,Accepted,Accepted,Queued,Queued,Queued,Completed,Accepted,Accepted,Accepted,Completed": 13, "Queued,Accepted,Accepted,Accepted,Completed,Accepted,Queued,Accepted,Queued,Accepted,Queued,Accepted,Queued": 75, "Queued,Accepted,Accepted,Accepted,Completed,Accepted,Queued,Accepted,Queued,Accepted,Queued,Completed,Completed": 75, "Queued,Accepted,Accepted,Queued,Accepted,Queued,Accepted,Accepted,Queued,Completed,Accepted,Completed,Accepted": 90, "Queued,Accepted,Completed,Completed,Completed,Completed,Completed,Queued,Queued,Unmatched,Accepted,Completed,Accepted": 33, "Queued,Queued,Queued,Accepted,Completed,Accepted,Accepted,Accepted,Completed,Completed,Queued,Accepted,Queued": 3, "Queued,Queued,Queued,Accepted,Completed,Accepted,Accepted,Accepted,Completed,Completed,Queued,Queued,Completed": 66, "Queued,Queued,Queued,Accepted,Completed,Accepted,Accepted,Queued,Accepted,Accepted,Accepted,Queued,Unmatched": 6, "Queued,Queued,Queued,Accepted,Completed,Accepted,Accepted,Queued,Accepted,Accepted,Completed,Completed,Completed": 42, "Queued,Queued,Queued,Accepted,Completed,Accepted,Accepted,Queued,Accepted,Queued,Queued,Completed,Accepted": 10, "Queued,Queued,Queued,Accepted,Completed,Accepted,Accepted,Queued,Accepted,Queued,Queued,Completed,Queued": 42, "Queued,Queued,Queued,Accepted,Completed,Accepted,Accepted,Queued,Accepted,Queued,Completed,Accepted,Queued": 217, "Queued,Queued,Queued,Accepted,Completed,Accepted,Accepted,Queued,Accepted,Queued,Completed,Completed,Accepted": 240, "Queued,Queued,Queued,Accepted,Completed,Accepted,Accepted,Queued,Accepted,Queued,Completed,Completed,Completed": 213, "Queued,Queued,Queued,Accepted,Completed,Accepted,Accepted,Queued,Accepted,Completed,Completed,Unmatched,Accepted": 39, "Accepted,Accepted,Accepted,Queued,Accepted,Accepted,Accepted,Accepted,Accepted,Accepted,Completed,Queued,Completed,Accepted": 24, "Accepted,Accepted,Accepted,Queued,Accepted,Accepted,Accepted,Accepted,Completed,Completed,Unmatched,Queued,Queued,Completed": 19, "Accepted,Accepted,Queued,Accepted,Accepted,Accepted,Accepted,Accepted,Accepted,Completed,Completed,Queued,Completed,Queued": 71, "Accepted,Accepted,Queued,Accepted,Accepted,Accepted,Accepted,Accepted,Accepted,Completed,Completed,Queued,Completed,Completed": 213, "Accepted,Accepted,Queued,Accepted,Accepted,Queued,Accepted,Queued,Accepted,Accepted,Completed,Completed,Queued,Accepted": 127, "Accepted,Accepted,Queued,Accepted,Accepted,Completed,Accepted,Accepted,Completed,Queued,Completed,Completed,Accepted,Accepted": 122, "Accepted,Accepted,Queued,Accepted,Accepted,Completed,Completed,Queued,Unmatched,Unmatched,Unmatched,Accepted,Queued,Completed": 67, "Accepted,Accepted,Queued,Accepted,Accepted,Completed,Completed,Queued,Unmatched,Unmatched,Unmatched,Accepted,Unmatched,Queued": 310, "Accepted,Accepted,Queued,Accepted,Queued,Accepted,Queued,Accepted,Queued,Accepted,Accepted,Completed,Queued,Queued": 270, "Accepted,Accepted,Queued,Accepted,Queued,Accepted,Queued,Accepted,Completed,Accepted,Accepted,Accepted,Completed,Unmatched": 55, "Accepted,Accepted,Queued,Queued,Completed,Completed,Completed,Accepted,Accepted,Accepted,Accepted,Queued,Completed,Queued": 6, "Accepted,Accepted,Queued,Queued,Completed,Completed,Completed,Accepted,Accepted,Queued,Completed,Unmatched,Completed,Accepted": 119, "Accepted,Accepted,Queued,Queued,Completed,Completed,Completed,Accepted,Queued,Completed,Accepted,Queued,Completed,Completed": 65, "Accepted,Accepted,Completed,Accepted,Queued,Accepted,Accepted,Queued,Completed,Queued,Completed,Accepted,Queued,Completed": 89, "Accepted,Accepted,Completed,Accepted,Queued,Accepted,Accepted,Completed,Queued,Queued,Completed,Accepted,Queued,Accepted": 54, "Accepted,Accepted,Completed,Accepted,Completed,Queued,Queued,Queued,Completed,Completed,Completed,Accepted,Accepted,Queued": 4, "Queued,Accepted,Accepted,Accepted,Completed,Accepted,Queued,Accepted,Queued,Accepted,Queued,Accepted,Queued,Accepted": 20, "Queued,Accepted,Completed,Completed,Completed,Completed,Completed,Queued,Queued,Unmatched,Accepted,Accepted,Accepted,Completed": 178, "Queued,Accepted,Completed,Completed,Completed,Completed,Completed,Queued,Queued,Unmatched,Accepted,Completed,Accepted,Accepted": 122, "Queued,Accepted,Completed,Completed,Completed,Completed,Completed,Queued,Queued,Unmatched,Accepted,Completed,Accepted,Completed": 262, "Queued,Queued,Queued,Accepted,Completed,Accepted,Accepted,Accepted,Completed,Completed,Queued,Queued,Completed,Completed": 71, "Queued,Queued,Queued,Accepted,Completed,Accepted,Accepted,Queued,Accepted,Accepted,Accepted,Unmatched,Accepted,Completed": 103, "Queued,Queued,Queued,Accepted,Completed,Accepted,Accepted,Queued,Accepted,Accepted,Accepted,Unmatched,Completed,Completed": 446, "Queued,Queued,Queued,Accepted,Completed,Accepted,Accepted,Queued,Accepted,Queued,Completed,Completed,Completed,Queued": 26, "Accepted,Accepted,Accepted,Queued,Accepted,Accepted,Accepted,Accepted,Accepted,Accepted,Completed,Queued,Completed,Accepted,Queued": 45, "Accepted,Accepted,Accepted,Queued,Accepted,Queued,Accepted,Accepted,Accepted,Accepted,Completed,Accepted,Completed,Accepted,Queued": 3, "Accepted,Accepted,Queued,Accepted,Accepted,Queued,Accepted,Queued,Accepted,Accepted,Completed,Accepted,Queued,Unmatched,Unmatched": 36, "Accepted,Accepted,Queued,Accepted,Accepted,Queued,Accepted,Queued,Accepted,Accepted,Completed,Completed,Queued,Accepted,Accepted": 68, "Accepted,Accepted,Queued,Accepted,Accepted,Queued,Accepted,Queued,Accepted,Accepted,Completed,Completed,Queued,Accepted,Queued": 15, "Accepted,Accepted,Queued,Accepted,Accepted,Completed,Accepted,Accepted,Completed,Queued,Completed,Completed,Queued,Accepted,Queued": 48, "Accepted,Accepted,Queued,Accepted,Accepted,Completed,Completed,Queued,Unmatched,Unmatched,Unmatched,Accepted,Unmatched,Queued,Completed": 293, "Accepted,Accepted,Queued,Accepted,Queued,Accepted,Queued,Accepted,Completed,Accepted,Accepted,Accepted,Completed,Accepted,Queued": 198, "Accepted,Accepted,Queued,Accepted,Queued,Accepted,Queued,Accepted,Completed,Completed,Accepted,Accepted,Unmatched,Completed,Accepted": 168, "Accepted,Accepted,Queued,Queued,Completed,Completed,Completed,Accepted,Accepted,Accepted,Accepted,Queued,Accepted,Accepted,Unmatched": 80, "Accepted,Accepted,Queued,Queued,Completed,Completed,Completed,Accepted,Accepted,Queued,Queued,Completed,Completed,Unmatched,Completed": 18, "Accepted,Accepted,Queued,Queued,Completed,Completed,Completed,Accepted,Accepted,Queued,Completed,Unmatched,Completed,Accepted,Completed": 125, "Accepted,Accepted,Queued,Queued,Completed,Completed,Completed,Accepted,Queued,Completed,Accepted,Queued,Completed,Completed,Queued": 3, "Accepted,Accepted,Completed,Accepted,Queued,Accepted,Accepted,Queued,Completed,Queued,Queued,Unmatched,Accepted,Accepted,Queued": 58, "Accepted,Accepted,Completed,Accepted,Queued,Accepted,Accepted,Queued,Completed,Queued,Completed,Accepted,Accepted,Unmatched,Completed": 72, "Accepted,Accepted,Completed,Accepted,Queued,Accepted,Accepted,Queued,Completed,Completed,Accepted,Queued,Queued,Completed,Accepted": 45, "Accepted,Accepted,Completed,Accepted,Queued,Accepted,Accepted,Queued,Completed,Completed,Accepted,Queued,Queued,Completed,Queued": 367, "Accepted,Accepted,Completed,Accepted,Completed,Queued,Queued,Queued,Completed,Completed,Completed,Accepted,Accepted,Queued,Completed": 64, "Queued,Accepted,Accepted,Accepted,Completed,Accepted,Queued,Accepted,Queued,Accepted,Queued,Queued,Queued,Queued,Queued": 267, "Queued,Accepted,Completed,Completed,Completed,Completed,Completed,Completed,Accepted,Queued,Queued,Unmatched,Completed,Completed,Accepted": 85, "Queued,Accepted,Completed,Completed,Completed,Completed,Completed,Completed,Accepted,Queued,Queued,Unmatched,Completed,Completed,Unmatched": 70, "Queued,Queued,Queued,Accepted,Completed,Accepted,Accepted,Accepted,Completed,Completed,Queued,Accepted,Unmatched,Completed,Queued": 105, "Queued,Queued,Queued,Accepted,Completed,Accepted,Accepted,Accepted,Completed,Completed,Queued,Queued,Completed,Queued,Queued": 143, "Queued,Queued,Queued,Accepted,Completed,Accepted,Accepted,Accepted,Completed,Completed,Queued,Queued,Completed,Queued,Completed": 51, "Queued,Queued,Queued,Accepted,Completed,Accepted,Accepted,Accepted,Completed,Completed,Queued,Queued,Completed,Queued,Unmatched": 91, "Queued,Queued,Queued,Accepted,Completed,Accepted,Accepted,Queued,Accepted,Queued,Completed,Completed,Accepted,Unmatched,Unmatched": 6, "Queued,Queued,Queued,Accepted,Completed,Accepted,Accepted,Queued,Accepted,Queued,Completed,Completed,Completed,Queued,Queued": 54, "Queued,Queued,Queued,Accepted,Completed,Accepted,Accepted,Queued,Accepted,Completed,Completed,Queued,Completed,Completed,Queued": 40, "Queued,Queued,Queued,Accepted,Completed,Accepted,Accepted,Queued,Accepted,Completed,Completed,Unmatched,Accepted,Accepted,Completed": 91, "Accepted,Accepted,Accepted,Queued,Accepted,Accepted,Accepted,Accepted,Accepted,Accepted,Completed,Queued,Completed,Accepted,Queued,Queued": 157, "Accepted,Accepted,Accepted,Queued,Accepted,Accepted,Accepted,Accepted,Accepted,Accepted,Completed,Queued,Completed,Accepted,Queued,Completed": 60, "Accepted,Accepted,Accepted,Queued,Accepted,Queued,Accepted,Accepted,Accepted,Accepted,Completed,Accepted,Completed,Accepted,Queued,Queued": 182, "Accepted,Accepted,Accepted,Queued,Accepted,Queued,Accepted,Accepted,Accepted,Accepted,Completed,Accepted,Completed,Accepted,Queued,Unmatched": 131, "Accepted,Accepted,Queued,Accepted,Accepted,Queued,Accepted,Queued,Accepted,Accepted,Completed,Completed,Queued,Accepted,Accepted,Accepted": 36, "Accepted,Accepted,Queued,Accepted,Accepted,Queued,Accepted,Queued,Accepted,Accepted,Completed,Completed,Queued,Accepted,Queued,Accepted": 215, "Accepted,Accepted,Queued,Accepted,Accepted,Queued,Accepted,Queued,Accepted,Accepted,Completed,Completed,Queued,Accepted,Queued,Unmatched": 228, "Accepted,Accepted,Queued,Accepted,Accepted,Queued,Accepted,Queued,Accepted,Accepted,Completed,Completed,Queued,Accepted,Unmatched,Accepted": 305, "Accepted,Accepted,Queued,Accepted,Accepted,Completed,Completed,Queued,Unmatched,Unmatched,Unmatched,Accepted,Unmatched,Queued,Completed,Completed": 13, "Accepted,Accepted,Queued,Accepted,Queued,Accepted,Queued,Accepted,Completed,Completed,Accepted,Accepted,Unmatched,Completed,Accepted,Queued": 26, "Accepted,Accepted,Queued,Accepted,Queued,Accepted,Queued,Accepted,Completed,Completed,Accepted,Accepted,Unmatched,Completed,Accepted,Completed": 26, "Accepted,Accepted,Completed,Accepted,Queued,Accepted,Accepted,Queued,Completed,Queued,Completed,Accepted,Accepted,Unmatched,Accepted,Queued": 52, "Accepted,Accepted,Completed,Accepted,Completed,Queued,Queued,Queued,Completed,Completed,Completed,Accepted,Queued,Unmatched,Queued,Accepted": 94, "Queued,Accepted,Accepted,Accepted,Completed,Accepted,Queued,Accepted,Queued,Accepted,Queued,Accepted,Queued,Completed,Completed,Accepted": 44, "Queued,Accepted,Accepted,Accepted,Completed,Accepted,Queued,Accepted,Queued,Accepted,Queued,Queued,Queued,Queued,Accepted,Queued": 158, "Queued,Accepted,Accepted,Accepted,Completed,Accepted,Queued,Accepted,Queued,Unmatched,Accepted,Queued,Queued,Completed,Unmatched,Unmatched": 38, "Queued,Accepted,Completed,Completed,Completed,Completed,Completed,Queued,Queued,Unmatched,Accepted,Accepted,Completed,Completed,Accepted,Completed": 23, "Queued,Queued,Queued,Accepted,Completed,Accepted,Accepted,Accepted,Accepted,Completed,Queued,Unmatched,Accepted,Completed,Accepted,Accepted": 472, "Queued,Queued,Queued,Accepted,Completed,Accepted,Accepted,Accepted,Completed,Completed,Queued,Accepted,Unmatched,Completed,Queued,Accepted": 25, "Queued,Queued,Queued,Accepted,Completed,Accepted,Accepted,Accepted,Completed,Completed,Queued,Queued,Completed,Queued,Accepted,Unmatched": 122, "Queued,Queued,Queued,Accepted,Completed,Accepted,Accepted,Accepted,Completed,Completed,Queued,Queued,Completed,Queued,Completed,Unmatched": 203, "Queued,Queued,Queued,Accepted,Completed,Accepted,Accepted,Accepted,Completed,Completed,Queued,Queued,Completed,Queued,Unmatched,Unmatched": 89, "Queued,Queued,Queued,Accepted,Completed,Accepted,Accepted,Queued,Accepted,Queued,Queued,Completed,Queued,Unmatched,Unmatched,Queued": 241, "Queued,Queued,Queued,Accepted,Completed,Accepted,Accepted,Queued,Accepted,Queued,Completed,Completed,Accepted,Unmatched,Queued,Accepted": 34, "Accepted,Accepted,Queued,Accepted,Accepted,Completed,Accepted,Accepted,Completed,Queued,Completed,Completed,Queued,Accepted,Accepted,Queued,Completed": 10, "Accepted,Accepted,Queued,Accepted,Queued,Accepted,Queued,Accepted,Queued,Accepted,Accepted,Completed,Queued,Queued,Completed,Accepted,Accepted": 12, "Accepted,Accepted,Queued,Accepted,Queued,Accepted,Queued,Accepted,Queued,Accepted,Accepted,Completed,Queued,Queued,Completed,Accepted,Completed": 13, "Accepted,Accepted,Queued,Queued,Completed,Completed,Completed,Accepted,Accepted,Queued,Completed,Unmatched,Completed,Accepted,Completed,Accepted,Accepted": 9, "Accepted,Accepted,Queued,Queued,Completed,Completed,Completed,Accepted,Accepted,Queued,Completed,Unmatched,Completed,Accepted,Completed,Accepted,Completed": 165, "Accepted,Accepted,Completed,Accepted,Queued,Accepted,Accepted,Queued,Completed,Completed,Accepted,Queued,Queued,Completed,Queued,Completed,Queued": 16, "Accepted,Accepted,Completed,Accepted,Queued,Accepted,Accepted,Queued,Completed,Completed,Accepted,Queued,Queued,Completed,Unmatched,Completed,Accepted": 92, "Accepted,Accepted,Completed,Accepted,Queued,Accepted,Accepted,Completed,Queued,Queued,Completed,Accepted,Queued,Accepted,Queued,Completed,Accepted": 2, "Queued,Accepted,Accepted,Accepted,Completed,Accepted,Queued,Accepted,Queued,Accepted,Queued,Queued,Queued,Queued,Accepted,Queued,Queued": 140, "Queued,Accepted,Accepted,Accepted,Completed,Accepted,Queued,Accepted,Queued,Accepted,Queued,Queued,Queued,Queued,Queued,Accepted,Queued": 6, "Queued,Accepted,Accepted,Accepted,Completed,Accepted,Queued,Accepted,Queued,Accepted,Queued,Queued,Queued,Queued,Completed,Queued,Accepted": 219, "Queued,Accepted,Completed,Completed,Completed,Completed,Completed,Queued,Queued,Unmatched,Accepted,Accepted,Completed,Completed,Accepted,Completed,Unmatched": 633, "Queued,Accepted,Completed,Completed,Completed,Completed,Completed,Completed,Accepted,Queued,Queued,Unmatched,Completed,Completed,Accepted,Queued,Completed": 337, "Queued,Queued,Queued,Accepted,Completed,Accepted,Accepted,Queued,Accepted,Queued,Queued,Queued,Completed,Queued,Unmatched,Accepted,Completed": 19, "Accepted,Accepted,Accepted,Queued,Accepted,Queued,Accepted,Accepted,Accepted,Accepted,Completed,Accepted,Completed,Accepted,Queued,Queued,Accepted,Unmatched": 331, "Accepted,Accepted,Accepted,Queued,Accepted,Queued,Accepted,Accepted,Accepted,Accepted,Completed,Accepted,Completed,Accepted,Completed,Completed,Completed,Queued": 97, "Accepted,Accepted,Queued,Accepted,Accepted,Queued,Accepted,Queued,Accepted,Accepted,Completed,Accepted,Queued,Unmatched,Unmatched,Unmatched,Completed,Accepted": 307, "Accepted,Accepted,Queued,Accepted,Accepted,Queued,Accepted,Queued,Accepted,Accepted,Completed,Completed,Queued,Accepted,Queued,Accepted,Completed,Completed": 427, "Accepted,Accepted,Queued,Accepted,Accepted,Completed,Accepted,Accepted,Completed,Queued,Completed,Completed,Queued,Accepted,Accepted,Queued,Accepted,Unmatched": 11, "Accepted,Accepted,Queued,Accepted,Queued,Accepted,Queued,Accepted,Queued,Accepted,Accepted,Completed,Queued,Queued,Completed,Accepted,Accepted,Accepted": 353, "Accepted,Accepted,Queued,Accepted,Queued,Accepted,Queued,Accepted,Queued,Accepted,Accepted,Completed,Queued,Queued,Completed,Accepted,Accepted,Completed": 47, "Accepted,Accepted,Queued,Accepted,Queued,Accepted,Queued,Accepted,Queued,Accepted,Accepted,Completed,Queued,Queued,Completed,Accepted,Completed,Completed": 30, "Accepted,Accepted,Queued,Accepted,Queued,Accepted,Queued,Accepted,Queued,Accepted,Accepted,Completed,Queued,Queued,Completed,Accepted,Completed,Unmatched": 73, "Accepted,Accepted,Completed,Accepted,Queued,Accepted,Accepted,Queued,Completed,Queued,Completed,Accepted,Accepted,Unmatched,Accepted,Completed,Unmatched,Unmatched": 195, "Accepted,Accepted,Completed,Accepted,Queued,Accepted,Accepted,Queued,Completed,Completed,Accepted,Queued,Queued,Completed,Unmatched,Completed,Accepted,Accepted": 65, "Accepted,Accepted,Completed,Accepted,Queued,Accepted,Accepted,Queued,Completed,Completed,Accepted,Queued,Queued,Completed,Unmatched,Completed,Completed,Completed": 28, "Accepted,Accepted,Completed,Accepted,Queued,Accepted,Accepted,Completed,Queued,Queued,Completed,Accepted,Queued,Accepted,Queued,Completed,Accepted,Queued": 21, "Queued,Accepted,Accepted,Accepted,Completed,Accepted,Queued,Accepted,Queued,Accepted,Queued,Accepted,Queued,Completed,Completed,Accepted,Queued,Accepted": 214, "Queued,Accepted,Accepted,Accepted,Completed,Accepted,Queued,Accepted,Queued,Accepted,Queued,Queued,Queued,Queued,Queued,Accepted,Accepted,Accepted": 223, "Queued,Accepted,Accepted,Accepted,Completed,Accepted,Queued,Accepted,Queued,Accepted,Queued,Queued,Queued,Queued,Completed,Queued,Queued,Completed": 144, "Queued,Accepted,Completed,Completed,Completed,Completed,Completed,Completed,Accepted,Queued,Queued,Unmatched,Completed,Completed,Accepted,Accepted,Unmatched,Accepted": 177, "Queued,Accepted,Completed,Completed,Completed,Completed,Completed,Completed,Accepted,Queued,Queued,Unmatched,Completed,Completed,Accepted,Completed,Completed,Completed": 37, "Accepted,Accepted,Accepted,Queued,Accepted,Queued,Accepted,Accepted,Accepted,Accepted,Completed,Accepted,Completed,Accepted,Queued,Queued,Unmatched,Accepted,Accepted": 245, "Accepted,Accepted,Accepted,Queued,Accepted,Queued,Accepted,Accepted,Accepted,Accepted,Completed,Accepted,Completed,Accepted,Completed,Unmatched,Accepted,Accepted,Completed": 18, "Accepted,Accepted,Queued,Accepted,Queued,Accepted,Queued,Accepted,Queued,Accepted,Accepted,Completed,Queued,Queued,Completed,Accepted,Accepted,Accepted,Accepted": 19, "Accepted,Accepted,Queued,Accepted,Queued,Accepted,Queued,Accepted,Queued,Accepted,Accepted,Completed,Queued,Queued,Completed,Accepted,Accepted,Accepted,Unmatched": 28, "Accepted,Accepted,Queued,Accepted,Queued,Accepted,Queued,Accepted,Queued,Accepted,Accepted,Completed,Queued,Queued,Completed,Accepted,Accepted,Completed,Accepted": 108, "Accepted,Accepted,Queued,Accepted,Queued,Accepted,Queued,Accepted,Queued,Accepted,Accepted,Completed,Queued,Queued,Completed,Accepted,Completed,Accepted,Completed": 66, "Accepted,Accepted,Queued,Accepted,Queued,Accepted,Queued,Accepted,Queued,Accepted,Accepted,Completed,Queued,Queued,Completed,Accepted,Completed,Accepted,Unmatched": 238, "Accepted,Accepted,Completed,Accepted,Queued,Accepted,Accepted,Completed,Queued,Queued,Completed,Accepted,Queued,Accepted,Queued,Completed,Accepted,Queued,Accepted": 95, "Queued,Accepted,Accepted,Accepted,Completed,Accepted,Queued,Accepted,Queued,Accepted,Queued,Accepted,Queued,Completed,Completed,Accepted,Queued,Accepted,Completed": 72, "Queued,Accepted,Accepted,Accepted,Completed,Accepted,Queued,Accepted,Queued,Accepted,Queued,Queued,Queued,Queued,Queued,Accepted,Accepted,Accepted,Completed": 13, "Queued,Accepted,Accepted,Accepted,Completed,Accepted,Queued,Accepted,Queued,Accepted,Queued,Queued,Queued,Queued,Completed,Queued,Queued,Completed,Accepted": 263, "Accepted,Accepted,Queued,Accepted,Accepted,Completed,Accepted,Accepted,Completed,Queued,Completed,Completed,Queued,Accepted,Accepted,Queued,Accepted,Accepted,Queued,Queued": 83, "Accepted,Accepted,Queued,Accepted,Queued,Accepted,Queued,Accepted,Queued,Accepted,Accepted,Completed,Queued,Queued,Completed,Accepted,Accepted,Accepted,Accepted,Completed": 3, "Accepted,Accepted,Queued,Accepted,Queued,Accepted,Queued,Accepted,Queued,Accepted,Accepted,Completed,Queued,Queued,Completed,Accepted,Accepted,Accepted,Queued,Accepted": 165, "Accepted,Accepted,Queued,Accepted,Queued,Accepted,Queued,Accepted,Queued,Accepted,Accepted,Completed,Queued,Queued,Completed,Accepted,Accepted,Accepted,Queued,Queued": 169, "Accepted,Accepted,Queued,Accepted,Queued,Accepted,Queued,Accepted,Queued,Accepted,Accepted,Completed,Queued,Queued,Completed,Accepted,Completed,Accepted,Completed,Queued": 21, "Accepted,Accepted,Queued,Accepted,Queued,Accepted,Queued,Accepted,Queued,Accepted,Accepted,Completed,Queued,Queued,Completed,Accepted,Completed,Completed,Accepted,Completed": 44, "Accepted,Accepted,Queued,Accepted,Queued,Accepted,Queued,Accepted,Completed,Accepted,Accepted,Accepted,Completed,Accepted,Queued,Unmatched,Unmatched,Unmatched,Completed,Accepted": 167, "Accepted,Accepted,Completed,Accepted,Queued,Accepted,Accepted,Completed,Queued,Queued,Completed,Accepted,Queued,Accepted,Queued,Completed,Accepted,Queued,Queued,Accepted": 123, "Accepted,Accepted,Completed,Accepted,Queued,Accepted,Accepted,Completed,Queued,Queued,Completed,Accepted,Queued,Accepted,Queued,Completed,Accepted,Queued,Queued,Completed": 224, "Accepted,Accepted,Completed,Accepted,Queued,Accepted,Accepted,Completed,Queued,Queued,Completed,Accepted,Queued,Accepted,Queued,Completed,Accepted,Unmatched,Queued,Completed": 22, "Queued,Accepted,Accepted,Accepted,Completed,Accepted,Queued,Accepted,Queued,Accepted,Queued,Queued,Queued,Queued,Queued,Accepted,Accepted,Completed,Accepted,Queued": 15, "Queued,Accepted,Accepted,Accepted,Completed,Accepted,Queued,Accepted,Queued,Accepted,Queued,Queued,Queued,Queued,Queued,Accepted,Accepted,Completed,Accepted,Unmatched": 5, "Queued,Accepted,Accepted,Accepted,Completed,Accepted,Queued,Accepted,Queued,Accepted,Queued,Queued,Queued,Queued,Completed,Queued,Queued,Completed,Accepted,Unmatched": 75, "Queued,Accepted,Accepted,Accepted,Completed,Accepted,Queued,Accepted,Queued,Accepted,Queued,Queued,Queued,Queued,Completed,Queued,Unmatched,Accepted,Queued,Unmatched": 8, "Accepted,Accepted,Accepted,Queued,Accepted,Queued,Accepted,Accepted,Accepted,Accepted,Completed,Accepted,Completed,Accepted,Queued,Queued,Unmatched,Accepted,Accepted,Queued,Accepted": 10, "Accepted,Accepted,Queued,Accepted,Queued,Accepted,Queued,Accepted,Queued,Accepted,Accepted,Completed,Queued,Queued,Completed,Accepted,Completed,Accepted,Completed,Completed,Unmatched": 6, "Accepted,Accepted,Queued,Accepted,Queued,Accepted,Queued,Accepted,Queued,Accepted,Accepted,Completed,Queued,Queued,Completed,Accepted,Completed,Completed,Accepted,Completed,Unmatched": 160, "Accepted,Accepted,Completed,Accepted,Queued,Accepted,Accepted,Queued,Completed,Completed,Accepted,Queued,Queued,Completed,Unmatched,Completed,Completed,Completed,Completed,Unmatched,Accepted": 82, "Accepted,Accepted,Completed,Accepted,Queued,Accepted,Accepted,Completed,Queued,Queued,Completed,Accepted,Queued,Accepted,Queued,Completed,Accepted,Queued,Accepted,Accepted,Unmatched": 127, "Accepted,Accepted,Completed,Accepted,Queued,Accepted,Accepted,Completed,Queued,Queued,Completed,Accepted,Queued,Accepted,Queued,Completed,Accepted,Queued,Accepted,Queued,Accepted": 137, "Accepted,Accepted,Completed,Accepted,Queued,Accepted,Accepted,Completed,Queued,Queued,Completed,Accepted,Queued,Accepted,Queued,Completed,Completed,Accepted,Completed,Queued,Accepted": 5, "Accepted,Accepted,Completed,Accepted,Queued,Accepted,Accepted,Completed,Queued,Queued,Completed,Accepted,Queued,Accepted,Queued,Completed,Completed,Accepted,Completed,Queued,Completed": 181, "Queued,Accepted,Accepted,Accepted,Completed,Accepted,Queued,Accepted,Queued,Accepted,Queued,Queued,Queued,Queued,Queued,Accepted,Accepted,Accepted,Completed,Accepted,Accepted": 40, "Queued,Accepted,Accepted,Accepted,Completed,Accepted,Queued,Accepted,Queued,Accepted,Queued,Queued,Queued,Queued,Queued,Accepted,Accepted,Accepted,Completed,Completed,Accepted": 84, "Queued,Accepted,Accepted,Accepted,Completed,Accepted,Queued,Accepted,Queued,Accepted,Queued,Queued,Queued,Queued,Queued,Accepted,Accepted,Accepted,Completed,Completed,Unmatched": 26, "Accepted,Accepted,Accepted,Queued,Accepted,Queued,Accepted,Accepted,Accepted,Accepted,Completed,Accepted,Completed,Accepted,Completed,Unmatched,Accepted,Accepted,Completed,Completed,Completed,Accepted": 4, "Accepted,Accepted,Queued,Accepted,Accepted,Completed,Accepted,Accepted,Completed,Queued,Completed,Completed,Queued,Accepted,Accepted,Queued,Accepted,Accepted,Queued,Queued,Queued,Queued": 78, "Accepted,Accepted,Queued,Accepted,Accepted,Completed,Accepted,Accepted,Completed,Queued,Completed,Completed,Queued,Accepted,Accepted,Queued,Accepted,Accepted,Unmatched,Completed,Completed,Accepted": 80, "Accepted,Accepted,Queued,Accepted,Queued,Accepted,Queued,Accepted,Queued,Accepted,Accepted,Completed,Queued,Queued,Completed,Accepted,Completed,Accepted,Completed,Completed,Completed,Accepted": 155, "Accepted,Accepted,Queued,Accepted,Queued,Accepted,Queued,Accepted,Queued,Accepted,Accepted,Completed,Queued,Queued,Completed,Accepted,Completed,Accepted,Unmatched,Completed,Completed,Accepted": 147, "Accepted,Accepted,Queued,Accepted,Queued,Accepted,Queued,Accepted,Queued,Accepted,Accepted,Completed,Queued,Queued,Completed,Accepted,Completed,Completed,Queued,Queued,Completed,Completed": 131, "Accepted,Accepted,Completed,Accepted,Queued,Accepted,Accepted,Completed,Queued,Queued,Completed,Accepted,Queued,Accepted,Queued,Completed,Accepted,Queued,Queued,Accepted,Completed,Accepted": 342, "Queued,Accepted,Accepted,Accepted,Completed,Accepted,Queued,Accepted,Queued,Accepted,Queued,Queued,Queued,Queued,Queued,Accepted,Accepted,Accepted,Completed,Accepted,Accepted,Accepted": 16, "Accepted,Accepted,Queued,Accepted,Queued,Accepted,Queued,Accepted,Queued,Accepted,Accepted,Completed,Queued,Queued,Completed,Accepted,Completed,Accepted,Unmatched,Completed,Completed,Accepted,Accepted": 136, "Accepted,Accepted,Queued,Accepted,Queued,Accepted,Queued,Accepted,Queued,Accepted,Accepted,Completed,Queued,Queued,Completed,Accepted,Completed,Accepted,Unmatched,Completed,Completed,Accepted,Completed": 123, "Queued,Accepted,Accepted,Accepted,Completed,Accepted,Queued,Accepted,Queued,Accepted,Queued,Queued,Queued,Queued,Queued,Accepted,Accepted,Accepted,Completed,Accepted,Accepted,Accepted,Completed": 39, "Accepted,Accepted,Queued,Accepted,Accepted,Completed,Accepted,Accepted,Completed,Queued,Completed,Completed,Queued,Accepted,Accepted,Queued,Accepted,Accepted,Queued,Queued,Queued,Queued,Unmatched,Completed,Accepted": 95, "Accepted,Accepted,Queued,Accepted,Accepted,Completed,Accepted,Accepted,Completed,Queued,Completed,Completed,Queued,Accepted,Accepted,Queued,Accepted,Accepted,Queued,Queued,Queued,Queued,Unmatched,Completed,Queued": 26, "Accepted,Accepted,Queued,Accepted,Accepted,Completed,Accepted,Accepted,Completed,Queued,Completed,Completed,Queued,Accepted,Accepted,Queued,Accepted,Accepted,Queued,Queued,Queued,Queued,Unmatched,Completed": 5, "Accepted,Accepted,Queued,Accepted,Accepted,Completed,Accepted,Accepted,Completed,Queued,Completed,Completed,Queued,Accepted,Accepted,Queued,Accepted,Accepted,Queued,Queued,Queued,Completed,Queued,Queued,Accepted": 91, "Accepted,Accepted,Queued,Accepted,Accepted,Completed,Accepted,Accepted,Completed,Queued,Completed,Completed,Queued,Accepted,Accepted,Queued,Accepted,Accepted,Queued,Queued,Queued,Completed,Queued,Queued,Queued": 144, "Accepted,Accepted,Queued,Accepted,Accepted,Completed,Accepted,Accepted,Completed,Queued,Completed,Completed,Queued,Accepted,Accepted,Queued,Accepted,Accepted,Queued,Queued,Queued,Completed,Queued,Unmatched": 2, "Accepted,Accepted,Queued,Accepted,Queued,Accepted,Queued,Accepted,Queued,Accepted,Accepted,Completed,Queued,Queued,Completed,Accepted,Accepted,Accepted,Accepted,Accepted,Unmatched,Accepted,Completed,Accepted,Completed": 571, "Accepted,Accepted,Queued,Accepted,Queued,Accepted,Queued,Accepted,Queued,Accepted,Accepted,Completed,Queued,Queued,Completed,Accepted,Accepted,Accepted,Accepted,Accepted,Unmatched,Accepted,Completed,Accepted": 8, "Accepted,Accepted,Queued,Accepted,Queued,Accepted,Queued,Accepted,Queued,Accepted,Accepted,Completed,Queued,Queued,Completed,Accepted,Accepted,Accepted,Accepted,Accepted,Unmatched,Accepted,Completed,Completed,Accepted": 108, "Accepted,Accepted,Queued,Accepted,Queued,Accepted,Queued,Accepted,Queued,Accepted,Accepted,Completed,Queued,Queued,Completed,Accepted,Accepted,Accepted,Accepted,Accepted,Unmatched,Accepted,Completed,Completed,Queued": 15, "Accepted,Accepted,Queued,Accepted,Queued,Accepted,Queued,Accepted,Queued,Accepted,Accepted,Completed,Queued,Queued,Completed,Accepted,Accepted,Accepted,Accepted,Accepted,Unmatched,Accepted,Completed,Completed,Completed": 15, "Accepted,Accepted,Queued,Accepted,Queued,Accepted,Queued,Accepted,Queued,Accepted,Accepted,Completed,Queued,Queued,Completed,Accepted,Completed,Accepted,Unmatched,Completed,Completed,Accepted,Completed,Accepted,Accepted": 25, "Accepted,Accepted,Queued,Accepted,Queued,Accepted,Queued,Accepted,Queued,Accepted,Accepted,Completed,Queued,Queued,Completed,Accepted,Completed,Accepted,Unmatched,Completed,Completed,Accepted,Completed,Completed,Completed": 1, "Accepted,Accepted,Queued,Accepted,Queued,Accepted,Queued,Accepted,Queued,Accepted,Accepted,Completed,Queued,Queued,Completed,Accepted,Completed,Accepted,Unmatched,Completed,Completed,Accepted,Completed,Completed": 16, "Accepted,Accepted,Queued,Accepted,Queued,Accepted,Queued,Accepted,Queued,Accepted,Accepted,Completed,Queued,Queued,Completed,Accepted,Completed,Completed,Queued,Queued,Completed,Accepted,Accepted,Queued,Queued": 128, "Accepted,Accepted,Queued,Accepted,Queued,Accepted,Queued,Accepted,Queued,Accepted,Accepted,Completed,Queued,Queued,Completed,Accepted,Completed,Completed,Queued,Queued,Completed,Accepted,Accepted,Queued,Unmatched": 87, "Accepted,Accepted,Queued,Accepted,Queued,Accepted,Queued,Accepted,Queued,Accepted,Accepted,Completed,Queued,Queued,Completed,Accepted,Completed,Completed,Queued,Queued,Completed,Accepted,Accepted,Queued": 94, "Accepted,Accepted,Completed,Accepted,Queued,Accepted,Accepted,Completed,Queued,Queued,Completed,Accepted,Queued,Accepted,Queued,Completed,Completed,Accepted,Completed,Queued,Completed,Queued,Unmatched,Completed,Accepted": 52, "Accepted,Accepted,Completed,Accepted,Queued,Accepted,Accepted,Completed,Queued,Queued,Completed,Accepted,Queued,Accepted,Queued,Completed,Completed,Accepted,Completed,Queued,Completed,Queued,Unmatched,Completed,Completed": 53, "Accepted,Accepted,Completed,Accepted,Queued,Accepted,Accepted,Completed,Queued,Queued,Completed,Accepted,Queued,Accepted,Queued,Completed,Completed,Accepted,Completed,Queued,Completed,Queued,Unmatched,Unmatched,Unmatched": 241, "Queued,Accepted,Accepted,Accepted,Completed,Accepted,Queued,Accepted,Queued,Accepted,Queued,Queued,Queued,Queued,Queued,Accepted,Accepted,Accepted,Completed,Accepted,Accepted,Accepted,Completed,Completed,Accepted": 90, "Queued,Accepted,Accepted,Accepted,Completed,Accepted,Queued,Accepted,Queued,Accepted,Queued,Queued,Queued,Queued,Queued,Accepted,Accepted,Accepted,Completed,Accepted,Accepted,Accepted,Completed,Completed,Queued": 107, "Queued,Accepted,Accepted,Accepted,Completed,Accepted,Queued,Accepted,Queued,Accepted,Queued,Queued,Queued,Queued,Queued,Accepted,Accepted,Accepted,Completed,Accepted,Accepted,Accepted,Completed,Completed,Completed": 40, "Queued,Accepted,Accepted,Accepted,Completed,Accepted,Queued,Accepted,Queued,Accepted,Queued,Queued,Queued,Queued,Queued,Accepted,Accepted,Accepted,Completed,Accepted,Accepted,Accepted,Completed,Completed,Unmatched": 73, "Queued,Accepted,Accepted,Accepted,Completed,Accepted,Queued,Accepted,Queued,Accepted,Queued,Queued,Queued,Queued,Queued,Accepted,Accepted,Accepted,Completed,Accepted,Accepted,Accepted,Completed,Unmatched,Completed": 55, "Queued,Accepted,Accepted,Accepted,Completed,Accepted,Queued,Accepted,Queued,Accepted,Queued,Queued,Queued,Queued,Queued,Accepted,Accepted,Accepted,Completed,Accepted,Accepted,Accepted,Completed,Unmatched,Unmatched": 22, "Queued,Accepted,Accepted,Accepted,Completed,Accepted,Queued,Accepted,Queued,Accepted,Queued,Queued,Queued,Queued,Queued,Accepted,Accepted,Accepted,Completed,Completed,Accepted,Queued,Completed,Accepted,Accepted": 39, "Queued,Accepted,Accepted,Accepted,Completed,Accepted,Queued,Accepted,Queued,Accepted,Queued,Queued,Queued,Queued,Queued,Accepted,Accepted,Accepted,Completed,Completed,Accepted,Queued,Completed,Accepted,Queued": 123, "Queued,Accepted,Accepted,Accepted,Completed,Accepted,Queued,Accepted,Queued,Accepted,Queued,Queued,Queued,Queued,Queued,Accepted,Accepted,Accepted,Completed,Completed,Accepted,Queued,Completed,Accepted,Completed": 226, "Queued,Accepted,Accepted,Accepted,Completed,Accepted,Queued,Accepted,Queued,Accepted,Queued,Queued,Queued,Queued,Queued,Accepted,Accepted,Accepted,Completed,Completed,Accepted,Queued,Completed,Unmatched,Completed": 8}